[
  {
    "company": "한국경제매거진앤북",
    "name": "강성호",
    "department": "SRT 마케팅팀",
    "position": "부장",
    "email": "ksh77hhh@hankyung.com"
  },
  {
    "company": "한국경제매거진앤북",
    "name": "강은영",
    "department": "arte",
    "position": "기자",
    "email": "qboom@hankyung.com"
  },
  {
    "company": "한국경제매거진앤북",
    "name": "강홍민",
    "department": "hankyung JOB&JOY팀",
    "position": "차장",
    "email": "khm@hankyung.com"
  },
  {
    "company": "한국경제매거진앤북",
    "name": "구현화",
    "department": "한경ESG 편집국",
    "position": "기자",
    "email": "kuh@hankyung.com"
  },
  {
    "company": "한국경제매거진앤북",
    "name": "권미숙",
    "department": "한경ESG 편집국",
    "position": "차장",
    "email": "lipeyes@hankyung.com"
  },
  {
    "company": "한국경제매거진앤북",
    "name": "권석중",
    "department": "디자인팀(출판)",
    "position": "대리",
    "email": "juwith@hankyung.com"
  },
  {
    "company": "한국경제매거진앤북",
    "name": "김광희",
    "department": "SRT 마케팅팀",
    "position": "차장",
    "email": "kkh@hankyung.com"
  },
  {
    "company": "한국경제매거진앤북",
    "name": "김규성",
    "department": "콘텐츠기획2팀",
    "position": "",
    "email": "ks0508@hankyung.com"
  },
  {
    "company": "한국경제매거진앤북",
    "name": "김규형",
    "department": "홍보마케팅부",
    "position": "부장",
    "email": "ghkim@hankyung.com"
  },
  {
    "company": "한국경제매거진앤북",
    "name": "김기남",
    "department": "영상정보팀_한경BUSINESS",
    "position": "부장",
    "email": "knk@hankyung.com"
  },
  {
    "company": "한국경제매거진앤북",
    "name": "김명혁",
    "department": "경영지원팀(출판)",
    "position": "부장",
    "email": "fo0714@hankyung.com"
  },
  {
    "company": "한국경제매거진앤북",
    "name": "김민주",
    "department": "온라인전략팀",
    "position": "대리",
    "email": "minjoo@hankyung.com"
  },
  {
    "company": "한국경제매거진앤북",
    "name": "김보형",
    "department": "기자",
    "position": "파견",
    "email": "kph21c@hankyung.com"
  },
  {
    "company": "한국경제매거진앤북",
    "name": "김셀라",
    "department": "경영지원팀",
    "position": "과장",
    "email": "sellakim@hankyung.com"
  },
  {
    "company": "한국경제매거진앤북",
    "name": "김수정",
    "department": "한경MONEY 편집국",
    "position": "기자",
    "email": "hohokim@hankyung.com"
  },
  {
    "company": "한국경제매거진앤북",
    "name": "김승호",
    "department": "콘텐츠기획1팀",
    "position": "기자",
    "email": "zahir4@hankyung.com"
  },
  {
    "company": "한국경제매거진앤북",
    "name": "김영은",
    "department": "한경BUSINESS 편집국",
    "position": "사원",
    "email": "kye0218@hankyung.com"
  },
  {
    "company": "한국경제매거진앤북",
    "name": "김예나",
    "department": "한경BIO Insight팀",
    "position": "차장대우",
    "email": "yena@hankyung.com"
  },
  {
    "company": "한국경제매거진앤북",
    "name": "김은아B",
    "department": "여행팀",
    "position": "차장대우",
    "email": "una@hankyung.com"
  },
  {
    "company": "한국경제매거진앤북",
    "name": "김정우",
    "department": "한경BUSINESS 편집국",
    "position": "차장",
    "email": "enyou@hankyung.com"
  },
  {
    "company": "한국경제매거진앤북",
    "name": "김지수",
    "department": "콘텐츠기획2팀",
    "position": "기자",
    "email": "kimjisoo@hankyung.com"
  },
  {
    "company": "한국경제매거진앤북",
    "name": "김지은",
    "department": "arte",
    "position": "기자",
    "email": "jekim@hankyung.com"
  },
  {
    "company": "한국경제매거진앤북",
    "name": "김태림",
    "department": "한경BUSINESS 편집국",
    "position": "기자",
    "email": "tae@hankyung.com"
  },
  {
    "company": "한국경제매거진앤북",
    "name": "김형철",
    "department": "",
    "position": "파견",
    "email": "adhunter@hankyung.com"
  },
  {
    "company": "한국경제매거진앤북",
    "name": "김혜인",
    "department": "온라인전략팀",
    "position": "계약직",
    "email": "hyein51@hankyung.com"
  },
  {
    "company": "한국경제매거진앤북",
    "name": "남궁훈",
    "department": "기획편집1팀",
    "position": "사원",
    "email": "ngh96@hankyung.com"
  },
  {
    "company": "한국경제매거진앤북",
    "name": "남소현",
    "department": "디자인팀_한경MONEY",
    "position": "기자",
    "email": "nsh9509@hankyung.com"
  },
  {
    "company": "한국경제매거진앤북",
    "name": "마현숙",
    "department": "기획편집1팀",
    "position": "부장",
    "email": "mama0707@hankyung.com"
  },
  {
    "company": "한국경제매거진앤북",
    "name": "민보름",
    "department": "한경BUSINESS 편집국",
    "position": "기자",
    "email": "brmin@hankyung.com"
  },
  {
    "company": "한국경제매거진앤북",
    "name": "박경희",
    "department": "콘텐츠기획1팀",
    "position": "기자",
    "email": "gerrard@hankyung.com"
  },
  {
    "company": "한국경제매거진앤북",
    "name": "박도현",
    "department": "홍보마케팅부",
    "position": "대리",
    "email": "pdh0109@hankyung.com"
  },
  {
    "company": "한국경제매거진앤북",
    "name": "박명규",
    "department": "디자인팀_한경BUSINESS",
    "position": "차장",
    "email": "sawind81@hankyung.com"
  },
  {
    "company": "한국경제매거진앤북",
    "name": "박재문",
    "department": "arte&MONEY 마케팅팀",
    "position": "부국장대우",
    "email": "jemoon2@hankyung.com"
  },
  {
    "company": "한국경제매거진앤북",
    "name": "박정원",
    "department": "한경BUSINESS 편집국",
    "position": "인턴",
    "email": "jason201477@hankyung.com"
  },
  {
    "company": "한국경제매거진앤북",
    "name": "박정현",
    "department": "기획편집2팀",
    "position": "사원",
    "email": "parkjh@hankyung.com"
  },
  {
    "company": "한국경제매거진앤북",
    "name": "박진원",
    "department": "경영지원팀",
    "position": "과장",
    "email": "pjw@hankyung.com"
  },
  {
    "company": "한국경제매거진앤북",
    "name": "배현의",
    "department": "한경BUSINESS 편집국",
    "position": "인턴",
    "email": "baehyeonui@hankyung.com"
  },
  {
    "company": "한국경제매거진앤북",
    "name": "백상아",
    "department": "저작권팀",
    "position": "과장",
    "email": "sarah@hankyung.com"
  },
  {
    "company": "한국경제매거진앤북",
    "name": "서덕아",
    "department": "온라인전략팀",
    "position": "과장",
    "email": "daseo@hankyung.com"
  },
  {
    "company": "한국경제매거진앤북",
    "name": "서범세",
    "department": "영상정보팀_한경BUSINESS",
    "position": "국장대우",
    "email": "joycine@hankyung.com"
  },
  {
    "company": "한국경제매거진앤북",
    "name": "서은실",
    "department": "홍보마케팅부",
    "position": "과장",
    "email": "ess0317@hankyung.com"
  },
  {
    "company": "한국경제매거진앤북",
    "name": "서정환",
    "department": "임원실",
    "position": "",
    "email": "ceoseo@hankyung.com"
  },
  {
    "company": "한국경제매거진앤북",
    "name": "송시호",
    "department": "경영지원팀(출판)",
    "position": "사원",
    "email": "ssh@hankyung.com"
  },
  {
    "company": "한국경제매거진앤북",
    "name": "송영",
    "department": "디자인팀_한경BUSINESS",
    "position": "차장",
    "email": "syhs@hankyung.com"
  },
  {
    "company": "한국경제매거진앤북",
    "name": "신정은",
    "department": "콘텐츠기획2팀",
    "position": "차장",
    "email": "sh961443@hankyung.com"
  },
  {
    "company": "한국경제매거진앤북",
    "name": "신효영",
    "department": "SRT 마케팅팀",
    "position": "대리",
    "email": "shin567@hankyung.com"
  },
  {
    "company": "한국경제매거진앤북",
    "name": "안옥희",
    "department": "한경BUSINESS 편집국",
    "position": "기자",
    "email": "ahnoh05@hankyung.com"
  },
  {
    "company": "한국경제매거진앤북",
    "name": "양정원",
    "department": "한경MONEY 편집국",
    "position": "부장",
    "email": "neiro@hankyung.com"
  },
  {
    "company": "한국경제매거진앤북",
    "name": "엄주혜",
    "department": "콘텐츠기획1팀",
    "position": "사원",
    "email": "juhye94@hankyung.com"
  },
  {
    "company": "한국경제매거진앤북",
    "name": "오은환",
    "department": "기획편집2팀",
    "position": "대리",
    "email": "eunhwan@hankyung.com"
  },
  {
    "company": "한국경제매거진앤북",
    "name": "유연무",
    "department": "교열팀",
    "position": "기자",
    "email": "yoom2023@hankyung.com"
  },
  {
    "company": "한국경제매거진앤북",
    "name": "이미경",
    "department": "한경ESG 편집국",
    "position": "차장",
    "email": "esit917@hankyung.com"
  },
  {
    "company": "한국경제매거진앤북",
    "name": "이민희",
    "department": "콘텐츠기획1팀",
    "position": "사원",
    "email": "minhee@hankyung.com"
  },
  {
    "company": "한국경제매거진앤북",
    "name": "이선정",
    "department": "콘텐츠기획1팀",
    "position": "국장",
    "email": "sjlgh@hankyung.com"
  },
  {
    "company": "한국경제매거진앤북",
    "name": "이승균",
    "department": "한경ESG 편집국",
    "position": "차장대우",
    "email": "csr@hankyung.com"
  },
  {
    "company": "한국경제매거진앤북",
    "name": "이승률",
    "department": "한경MONEY 편집국",
    "position": "차장",
    "email": "ujh8817@hankyung.com"
  },
  {
    "company": "한국경제매거진앤북",
    "name": "이승욱",
    "department": "디자인팀(출판)",
    "position": "차장",
    "email": "solee@hankyung.com"
  },
  {
    "company": "한국경제매거진앤북",
    "name": "이승재",
    "department": "영상정보팀_한경MONEY",
    "position": "부국장대우",
    "email": "fotoleesj@hankyung.com"
  },
  {
    "company": "한국경제매거진앤북",
    "name": "이여진",
    "department": "홍보마케팅부",
    "position": "대리",
    "email": "lygin729@hankyung.com"
  },
  {
    "company": "한국경제매거진앤북",
    "name": "이준석",
    "department": "한경BUSINESS 마케팅팀",
    "position": "국장",
    "email": "hole1872@hankyung.com"
  },
  {
    "company": "한국경제매거진앤북",
    "name": "이진아",
    "department": "독자서비스팀",
    "position": "차장",
    "email": "jina0811@hankyung.com"
  },
  {
    "company": "한국경제매거진앤북",
    "name": "이진호",
    "department": "hankyung JOB&JOY팀",
    "position": "차장",
    "email": "jinho2323@hankyung.com"
  },
  {
    "company": "한국경제매거진앤북",
    "name": "이채미",
    "department": "경영지원팀(출판)",
    "position": "차장",
    "email": "chaem@hankyung.com"
  },
  {
    "company": "한국경제매거진앤북",
    "name": "이현주",
    "department": "한경MONEY 편집국",
    "position": "차장",
    "email": "charis@hankyung.com"
  },
  {
    "company": "한국경제매거진앤북",
    "name": "이혜영",
    "department": "기획편집2팀",
    "position": "차장",
    "email": "mwd101@hankyung.com"
  },
  {
    "company": "한국경제매거진앤북",
    "name": "이홍표",
    "department": "한경BUSINESS 편집국",
    "position": "부국장대우",
    "email": "hawlling@hankyung.com"
  },
  {
    "company": "한국경제매거진앤북",
    "name": "장승규",
    "department": "한경MONEY 편집국",
    "position": "국장",
    "email": "skjang@hankyung.com"
  },
  {
    "company": "한국경제매거진앤북",
    "name": "장철용",
    "department": "arte&MONEY 마케팅팀",
    "position": "부장대우",
    "email": "cyjang@hankyung.com"
  },
  {
    "company": "한국경제매거진앤북",
    "name": "정갑철",
    "department": "경영지원팀",
    "position": "국장",
    "email": "ttangaby@hankyung.com"
  },
  {
    "company": "한국경제매거진앤북",
    "name": "정다운",
    "department": "디자인팀_한경BUSINESS",
    "position": "기자",
    "email": "wjdekdns907@hankyung.com"
  },
  {
    "company": "한국경제매거진앤북",
    "name": "정락훈",
    "department": "한경BUSINESS 마케팅팀",
    "position": "대리",
    "email": "jrh1009@hankyung.com"
  },
  {
    "company": "한국경제매거진앤북",
    "name": "정복녀",
    "department": "독자서비스팀",
    "position": "차장",
    "email": "power96@hankyung.com"
  },
  {
    "company": "한국경제매거진앤북",
    "name": "정상미",
    "department": "여행팀",
    "position": "차장",
    "email": "nabi@hankyung.com"
  },
  {
    "company": "한국경제매거진앤북",
    "name": "정유진",
    "department": "디지털뉴스팀",
    "position": "차장",
    "email": "jinjin@hankyung.com"
  },
  {
    "company": "한국경제매거진앤북",
    "name": "정채희",
    "department": "한경BUSINESS 편집국",
    "position": "차장대우",
    "email": "poof34@hankyung.com"
  },
  {
    "company": "한국경제매거진앤북",
    "name": "정초원",
    "department": "한경MONEY 편집국",
    "position": "기자",
    "email": "ccw@hankyung.com"
  },
  {
    "company": "한국경제매거진앤북",
    "name": "정혜영",
    "department": "콘텐츠기획1팀",
    "position": "차장",
    "email": "hy5412@hankyung.com"
  },
  {
    "company": "한국경제매거진앤북",
    "name": "조경내",
    "department": "한경BUSINESS 마케팅팀",
    "position": "부장",
    "email": "cho501@hankyung.com"
  },
  {
    "company": "한국경제매거진앤북",
    "name": "조종현",
    "department": "제작지원팀",
    "position": "과장",
    "email": "chojh@hankyung.com"
  },
  {
    "company": "한국경제매거진앤북",
    "name": "차민경",
    "department": "경영지원팀",
    "position": "대리",
    "email": "wjsck45@hankyung.com"
  },
  {
    "company": "한국경제매거진앤북",
    "name": "최수진",
    "department": "한경BUSINESS 편집국",
    "position": "기자",
    "email": "jinny0618@hankyung.com"
  },
  {
    "company": "한국경제매거진앤북",
    "name": "최승헌",
    "department": "기획편집1팀",
    "position": "과장",
    "email": "shchoi@hankyung.com"
  },
  {
    "company": "한국경제매거진앤북",
    "name": "최정욱",
    "department": "경영지원팀",
    "position": "차장",
    "email": "wjddnr80@hankyung.com"
  },
  {
    "company": "한국경제매거진앤북",
    "name": "표자영",
    "department": "디자인팀_한경MONEY",
    "position": "차장",
    "email": "pjy@hankyung.com"
  },
  {
    "company": "한국경제매거진앤북",
    "name": "한용섭",
    "department": "한경ESG 편집국",
    "position": "부국장",
    "email": "poem1970@hankyung.com"
  },
  {
    "company": "한국경제매거진앤북",
    "name": "허미정",
    "department": "온라인전략팀",
    "position": "대리",
    "email": "hmj07@hankyung.com"
  },
  {
    "company": "한국경제매거진앤북",
    "name": "현예림",
    "department": "콘텐츠기획1팀",
    "position": "사원",
    "email": "hyunyerim@hankyung.com"
  },
  {
    "company": "한국경제매거진앤북",
    "name": "황진아B",
    "department": "콘텐츠기획2팀",
    "position": "기자",
    "email": "hja@hankyung.com"
  }
]